.gitignore
.pre-commit-config.yaml
.pylintrc
.readthedocs.yaml
CODE_OF_CONDUCT.md
LICENSE
README.rst
README.rst.license
requirements.txt
setup.py
sparkfun_qwiicas3935.py
.github/PULL_REQUEST_TEMPLATE/adafruit_circuitpython_pr.md
.github/workflows/build.yml
.github/workflows/failure-help-text.yml
.github/workflows/release.yml
LICENSES/CC-BY-4.0.txt
LICENSES/MIT.txt
LICENSES/Unlicense.txt
docs/api.rst
docs/api.rst.license
docs/conf.py
docs/examples.rst
docs/examples.rst.license
docs/index.rst
docs/index.rst.license
docs/requirements.txt
docs/_static/favicon.ico
docs/_static/favicon.ico.license
examples/example1_basic_lightning_i2c.py
examples/example1_basic_lightning_spi.py
examples/example2_more_lightning_features_i2c.py
examples/example2_more_lightning_features_spi.py
examples/example3_tune_antenna_i2c.py
examples/example3_tune_antenna_spi.py
examples/qwiicas3935_simpletest.py
sparkfun_circuitpython_qwiicas3935.egg-info/PKG-INFO
sparkfun_circuitpython_qwiicas3935.egg-info/SOURCES.txt
sparkfun_circuitpython_qwiicas3935.egg-info/dependency_links.txt
sparkfun_circuitpython_qwiicas3935.egg-info/requires.txt
sparkfun_circuitpython_qwiicas3935.egg-info/top_level.txt