Metadata-Version: 2.1
Name: sparkfun-circuitpython-qwiicas3935
Version: 1.0.7
Summary: CircuitPython driver library for the Sparkfun AS3935 Lightning Detector
Home-page: https://github.com/fourstix/Sparkfun_CircuitPython_QwiicAS3935
Author: Gaston Williams
Author-email: fourstix@gmail.com
License: MIT
Keywords: adafruit blinka circuitpython micropython qwiicas3935 sparkfun as3935 lightning
Platform: UNKNOWN
Classifier: Development Status :: 3 - Alpha
Classifier: Intended Audience :: Developers
Classifier: Topic :: Software Development :: Libraries
Classifier: Topic :: System :: Hardware
Classifier: License :: OSI Approved :: MIT License
Classifier: Programming Language :: Python :: 3
Classifier: Programming Language :: Python :: 3.4
Classifier: Programming Language :: Python :: 3.5
License-File: LICENSE
